<fest:template xmlns:fest="http://fest.mail.ru" context_name="json">
	<fest:script>
		console.log('[toolbar template]', json);
	</fest:script>
	<div class="bar-top {json.session.isSignedIn ? 'sas' : 'bar-top_invisible'}">
		<div class="bar-top__avatar">
			<i class="fa fa-user bar-top__avatar-placeholder" aria-hidden="true"></i>
			<!-- <img class="bar-top__avatar-img" src="images/nitr2.jpg" alt=""/> -->
		</div>
		<div class="bar-top__name">
			<span><fest:value>json.user.login</fest:value></span>
		</div>
		<div class="bar-top__logout">
			<button class="btn-logout js-logout" title="Logout"><i class="fa fa-sign-out"></i></button>
		</div>
	</div>
</fest:template>